mensajes/__init__.py
mensajes/adios/__init__.py
mensajes/adios/despedidas.py
mensajes/hola/saludos.py
Mensajes_aronca1998-6.0.dist-info/LICENSE
Mensajes_aronca1998-6.0.dist-info/METADATA
Mensajes_aronca1998-6.0.dist-info/WHEEL
Mensajes_aronca1998-6.0.dist-info/top_level.txt
Mensajes_aronca1998-6.0.dist-info/RECORD
