Metadata-Version: 2.1
Name: Mensajes-aronca1998
Version: 6.0
Summary: Un paquete para saludar y despedir
Home-page: https://www.aron.es
Author: Arón Carballo Álvares
Author-email: aronca1998@gmail.com
License-File: LICENSE
Requires-Dist: numpy (>=1.24.2)
